{
  "_format": "hh-sol-cache-2",
  "files": {
    "/Users/pedrosaragossy/Workspace/monad hacka/nqg-monad/contracts/NQGVoting.sol": {
      "lastModificationDate": 1774202347098,
      "contentHash": "c14722ef4691a41588d4d963092187d2",
      "sourceName": "contracts/NQGVoting.sol",
      "solcConfig": {
        "version": "0.8.24",
        "settings": {
          "evmVersion": "paris",
          "optimizer": {
            "enabled": false,
            "runs": 200
          },
          "outputSelection": {
            "*": {
              "*": [
                "abi",
                "evm.bytecode",
                "evm.deployedBytecode",
                "evm.methodIdentifiers",
                "metadata"
              ],
              "": [
                "ast"
              ]
            }
          }
        }
      },
      "imports": [],
      "versionPragmas": [
        "^0.8.24"
      ],
      "artifacts": [
        "NQGVoting"
      ]
    }
  }
}
